README.txt
ez_setup.py
setup.py
whs.commons.patterns.egg-info/PKG-INFO
whs.commons.patterns.egg-info/SOURCES.txt
whs.commons.patterns.egg-info/dependency_links.txt
whs.commons.patterns.egg-info/namespace_packages.txt
whs.commons.patterns.egg-info/top_level.txt
whs/commons/patterns/__init__.py
whs/commons/patterns/enum.py
whs/commons/patterns/flyweight.py
whs/commons/patterns/singleton.py